odoo/addons/product_variant_attribute_name_manager/README.rst
odoo/addons/product_variant_attribute_name_manager/__init__.py
odoo/addons/product_variant_attribute_name_manager/__manifest__.py
odoo/addons/product_variant_attribute_name_manager/i18n/product_variant_attribute_name_manager.pot
odoo/addons/product_variant_attribute_name_manager/models/__init__.py
odoo/addons/product_variant_attribute_name_manager/models/product_attribute.py
odoo/addons/product_variant_attribute_name_manager/readme/CONTRIBUTORS.rst
odoo/addons/product_variant_attribute_name_manager/readme/DESCRIPTION.rst
odoo/addons/product_variant_attribute_name_manager/static/description/icon.png
odoo/addons/product_variant_attribute_name_manager/static/description/index.html
odoo/addons/product_variant_attribute_name_manager/tests/__init__.py
odoo/addons/product_variant_attribute_name_manager/tests/test_product_variant_attribute_name_manager.py
odoo/addons/product_variant_attribute_name_manager/views/product_variant_attribute_name_manager_view.xml
odoo13_addon_product_variant_attribute_name_manager-13.0.3.0.0.dist-info/METADATA
odoo13_addon_product_variant_attribute_name_manager-13.0.3.0.0.dist-info/WHEEL
odoo13_addon_product_variant_attribute_name_manager-13.0.3.0.0.dist-info/top_level.txt
odoo13_addon_product_variant_attribute_name_manager-13.0.3.0.0.dist-info/RECORD
