Metadata-Version: 2.1
Name: odoo13-addon-product-variant-attribute-name-manager
Version: 13.0.3.0.0
Summary: Manage how to display the attributes on the product variant name.
Home-page: https://github.com/OCA/product-attribute
Author: ForgeFlow, Odoo Community Association (OCA)
Author-email: support@odoo-community.org
License: AGPL-3
Platform: UNKNOWN
Classifier: Programming Language :: Python
Classifier: Framework :: Odoo
Classifier: Framework :: Odoo :: 13.0
Classifier: License :: OSI Approved :: GNU Affero General Public License v3
Requires-Python: >=3.5
Requires-Dist: odoo (<13.1dev,>=13.0a)
